lib_name/__init__.py
lib_name/capstonePreprocessing.py
capstonePreprocessing-0.0.1.dist-info/METADATA
capstonePreprocessing-0.0.1.dist-info/WHEEL
capstonePreprocessing-0.0.1.dist-info/top_level.txt
capstonePreprocessing-0.0.1.dist-info/RECORD
